githistorian/VERSION
githistorian/__init__.py
githistorian/__main__.py
githistorian/alternate.py
githistorian/column.py
githistorian/githistorian.py
githistorian/graph.py
githistorian/layout.py
githistorian/node.py
githistorian/option.py
githistorian/row.py
githistorian/hunter/__init__.py
githistorian/hunter/head.py
githistorian/hunter/history.py
githistorian-0.1.3.dist-info/LICENSE
githistorian-0.1.3.dist-info/METADATA
githistorian-0.1.3.dist-info/WHEEL
githistorian-0.1.3.dist-info/entry_points.txt
githistorian-0.1.3.dist-info/top_level.txt
githistorian-0.1.3.dist-info/RECORD
