Metadata-Version: 2.1
Name: githistorian
Version: 0.1.3
Summary: Graph visualizer for git history
Home-page: https://github.com/drachlyznardh/githistorian
Author: Ivan Simonini
Author-email: drachlyznardh@gmail.com
License: UNKNOWN
Platform: UNKNOWN
Classifier: Programming Language :: Python :: 3
Classifier: License :: OSI Approved :: MIT License
Classifier: Operating System :: OS Independent
Requires-Dist: bintrees
